README.md
setup.py
toolbox/__init__.py
toolbox/decorators.py
toolbox/mixins.py
toolbox/utils.py
zhsq_toolbox.egg-info/PKG-INFO
zhsq_toolbox.egg-info/SOURCES.txt
zhsq_toolbox.egg-info/dependency_links.txt
zhsq_toolbox.egg-info/not-zip-safe
zhsq_toolbox.egg-info/requires.txt
zhsq_toolbox.egg-info/top_level.txt